nitro_pandas/__init__.py
nitro_pandas/dataframe.py
nitro_pandas/lazyframe.py
nitro_pandas/io/__init__.py
nitro_pandas/io/csv.py
nitro_pandas/io/excel.py
nitro_pandas/io/json.py
nitro_pandas/io/parquet.py
nitro_pandas-0.1.4.dist-info/METADATA
nitro_pandas-0.1.4.dist-info/WHEEL
nitro_pandas-0.1.4.dist-info/licenses/LICENSE
nitro_pandas-0.1.4.dist-info/RECORD
