Metadata-Version: 2.4
Name: nitro-pandas
Version: 0.1.4
Summary: A pandas-like API wrapper around Polars for high-performance data manipulation
Project-URL: Homepage, https://github.com/Wassim17Labdi/nitro-pandas
Project-URL: Repository, https://github.com/Wassim17Labdi/nitro-pandas
Project-URL: Documentation, https://github.com/Wassim17Labdi/nitro-pandas#readme
Project-URL: Issues, https://github.com/Wassim17Labdi/nitro-pandas/issues
Project-URL: Source Code, https://github.com/Wassim17Labdi/nitro-pandas
Author-email: Labdi Wassim <labdiwassim18@gmail.com>
License: MIT
License-File: LICENSE
Keywords: data-analysis,dataframe,pandas,performance,polars
Requires-Python: >=3.11
Requires-Dist: fastexcel>=0.7.0
Requires-Dist: openpyxl>=3.1.5
Requires-Dist: pandas>=2.2.3
Requires-Dist: polars>=1.30.0
Requires-Dist: pyarrow>=20.0.0
